barra_risk_model/Bias_stats.py
barra_risk_model/Factor_matrix_core.py
barra_risk_model/Specific_matrix_core.py
barra_risk_model/__init__.py
barra_risk_model/Factor_manufacture/__init__ .py
barra_risk_model/Factor_manufacture/descriptor_integration.py
barra_risk_model/Factor_manufacture/make_factor.py
barra_risk_model/Factor_manufacture/make_growth.py
barra_risk_model/Factor_return/Factor_return_core.py
barra_risk_model/Factor_return/__init__.py
barra_risk_model/Wind_update/__init__ .py
barra_risk_model/Wind_update/get_wind.py
barra_risk_model/Wind_update/load_descriptor.py
barra_risk_model/Wind_update/load_descriptor_daily.py
barra_risk_model/Wind_update/load_descriptor_seasonal.py
barra_risk_model/Wind_update/load_dt_rf.py
barra_risk_model/Wind_update/load_growth.py
barra_risk_model/Wind_update/load_index.py
barra_risk_model/Wind_update/load_pool_weight.py
barra_risk_model/Wind_update/load_totalA.py
barra_risk_model/common/__init__.py
barra_risk_model/common/cprint.py
barra_risk_model/common/set_path.py
barra_risk_model-0.1.5.dist-info/DESCRIPTION.rst
barra_risk_model-0.1.5.dist-info/METADATA
barra_risk_model-0.1.5.dist-info/RECORD
barra_risk_model-0.1.5.dist-info/WHEEL
barra_risk_model-0.1.5.dist-info/metadata.json
barra_risk_model-0.1.5.dist-info/top_level.txt
