Metadata-Version: 2.0
Name: barra-risk-model
Version: 0.1.5
Summary: Barra Risk Model CN version
Home-page: UNKNOWN
Author: Yili Peng
Author-email: yili_peng@outlook.com
License: UNKNOWN
Platform: UNKNOWN
Requires-Dist: RNWS (>=0.1.0)
